<climate_report><title>Rover Environmental Monitoring Station weather report</title><link>https://cab.inta-csic.es/rems/</link>
<record>
	<sol>15</sol>
	<terrestrial_date>Aug 22, 2012</terrestrial_date>
	<magnitudes>
		<min_temp>-78</min_temp>
		<max_temp>-1</max_temp>
		<pressure>7.3</pressure>
		<pressure_string>Lower</pressure_string>
		<abs_humidity>--</abs_humidity>
		<wind_speed>2</wind_speed>
		<wind_direction>E</wind_direction>
		<atmo_opacity>Sunny</atmo_opacity>
		<season>Month 6</season>
		<ls>159</ls>
		<sunrise>6 am</sunrise>
		<sunset>5 pm</sunset>
	</magnitudes>
</record>
<record><sol>16</sol><terrestrial_date>Aug 23, 2012</terrestrial_date><magnitudes><min_temp>-76</min_temp><max_temp>0</max_temp><pressure>7.4</pressure><pressure_string>Lower</pressure_string><abs_humidity>--</abs_humidity><wind_speed>2</wind_speed><wind_direction>E</wind_direction><atmo_opacity>Sunny</atmo_opacity><season>Month 6</season><ls>159</ls><sunrise>6 am</sunrise><sunset>5 pm</sunset></magnitudes></record><record><sol>19</sol><terrestrial_date>Aug 25, 2012</terrestrial_date><magnitudes><min_temp>-78</min_temp><max_temp>-18</max_temp><pressure>7.85</pressure><pressure_string>Lower</pressure_string><abs_humidity>--</abs_humidity><wind_speed>2</wind_speed><wind_direction>E</wind_direction><atmo_opacity>Sunny</atmo_opacity><season>Month 6</season><ls>160</ls><sunrise>6 am</sunrise><sunset>5 pm</sunset></magnitudes></record><record><sol>21</sol><terrestrial_date>Aug 27, 2012</terrestrial_date><magnitudes><min_temp>-73</min_temp><max_temp>0</max_temp><pressure>7.9</pressure><pressure_string>Lower</pressure_string><abs_humidity>--</abs_humidity><wind_speed>2</wind_speed><wind_direction>E</wind_direction><atmo_opacity>Sunny</atmo_opacity><season>Month 6</season><ls>161</ls><sunrise>6 am</sunrise><sunset>5 pm</sunset></magnitudes></record><record><sol>23</sol><terrestrial_date>Aug 29, 2012</terrestrial_date><magnitudes><min_temp>-73</min_temp><max_temp>0</max_temp><pressure>7.4</pressure><pressure_string>Lower</pressure_string><abs_humidity>xx</abs_humidity><wind_speed>2</wind_speed><wind_direction>E</wind_direction><atmo_opacity>Sunny</atmo_opacity><season>Month 6</season><ls>163</ls><sunrise>6 am</sunrise><sunset>5 pm</sunset></magnitudes></record><record><sol>22</sol><terrestrial_date>Aug 28, 2012</terrestrial_date><magnitudes><min_temp>-70</min_temp><max_temp>0</max_temp><pressure>7.4</pressure><pressure_string>Lower</pressure_string><abs_humidity>--</abs_humidity><wind_speed>2</wind_speed><wind_direction>E</wind_direction><atmo_opacity>Sunny</atmo_opacity><season>Month 6</season><ls>162</ls><sunrise>6 am</sunrise><sunset>5 pm</sunset></magnitudes></record><record><sol>25</sol><terrestrial_date>Sept. 1, 2012</terrestrial_date><magnitudes><min_temp>-73</min_temp><max_temp>-2</max_temp><pressure>7.4</pressure><pressure_string>Lower</pressure_string><abs_humidity>xx</abs_humidity><wind_speed>2</wind_speed><wind_direction>E</wind_direction><atmo_opacity>Sunny</atmo_opacity><season>Month 6</season><ls>165</ls><sunrise>6 am</sunrise><sunset>5 pm</sunset></magnitudes></record><record><sol>25</sol><terrestrial_date>Sept. 1, 2012</terrestrial_date><magnitudes><min_temp>-75</min_temp><max_temp>2</max_temp><pressure>7.42</pressure><pressure_string>Higher</pressure_string><abs_humidity>--</abs_humidity><wind_speed>2</wind_speed><wind_direction>E</wind_direction><atmo_opacity>Sunny</atmo_opacity><season>Month 6</season><ls>162</ls><sunrise>6 am</sunrise><sunset>5 pm</sunset></magnitudes></record><record><sol>26</sol><terrestrial_date>Sept. 2, 2012</terrestrial_date><magnitudes><min_temp>-76</min_temp><max_temp>-1</max_temp><pressure>7.43</pressure><pressure_string>Higher</pressure_string><abs_humidity>--</abs_humidity><wind_speed>2</wind_speed><wind_direction>E</wind_direction><atmo_opacity>Sunny</atmo_opacity><season>Month 6</season><ls>164.8</ls><sunrise>6 am</sunrise><sunset>5 pm</sunset></magnitudes></record><record><sol>27</sol><terrestrial_date>Sept. 3, 2012</terrestrial_date><magnitudes><min_temp>-75</min_temp><max_temp>-6</max_temp><pressure>7.45</pressure><pressure_string>Higher</pressure_string><abs_humidity>--</abs_humidity><wind_speed>2</wind_speed><wind_direction>E</wind_direction><atmo_opacity>Sunny</atmo_opacity><season>Month 6</season><ls>165.2</ls><sunrise>6 am</sunrise><sunset>5 pm</sunset></magnitudes></record><record><sol>28</sol><terrestrial_date>Sept. 4, 2012</terrestrial_date><magnitudes><min_temp>-75</min_temp><max_temp>-7</max_temp><pressure>7.45</pressure><pressure_string>Higher</pressure_string><abs_humidity>--</abs_humidity><wind_speed>2</wind_speed><wind_direction>E</wind_direction><atmo_opacity>Sunny</atmo_opacity><season>Month 6</season><ls>166.3</ls><sunrise>6 am</sunrise><sunset>5 pm</sunset></magnitudes></record><record><sol>29</sol><terrestrial_date>Sept. 5, 2012</terrestrial_date><magnitudes><min_temp>-75</min_temp><max_temp>-2</max_temp><pressure>7.47</pressure><pressure_string>Higher</pressure_string><abs_humidity>--</abs_humidity><wind_speed>2</wind_speed><wind_direction>E</wind_direction><atmo_opacity>Sunny</atmo_opacity><season>Month 6</season><ls>166.4</ls><sunrise>6 am</sunrise><sunset>5 pm</sunset></magnitudes></record><record><sol>30</sol><terrestrial_date>Sept. 6, 2012</terrestrial_date><magnitudes><min_temp>-74</min_temp><max_temp>-3</max_temp><pressure>7.47</pressure><pressure_string>Higher</pressure_string><abs_humidity>--</abs_humidity><wind_speed>2</wind_speed><wind_direction>E</wind_direction><atmo_opacity>Sunny</atmo_opacity><season>Month 6</season><ls>167.4</ls><sunrise>6 am</sunrise><sunset>5 pm</sunset></magnitudes></record><record><sol>31</sol><terrestrial_date>Sept. 7, 2012</terrestrial_date><magnitudes><min_temp>-74</min_temp><max_temp>--</max_temp><pressure>7.42</pressure><pressure_string>Higher</pressure_string><abs_humidity>--</abs_humidity><wind_speed>2</wind_speed><wind_direction>E</wind_direction><atmo_opacity>Sunny</atmo_opacity><season>Month 6</season><ls>167.9</ls><sunrise>6 am</sunrise><sunset>5 pm</sunset></magnitudes></record><record><sol>32</sol><terrestrial_date>Sept. 8, 2012</terrestrial_date><magnitudes><min_temp>-73</min_temp><max_temp>-2</max_temp><pressure>7.48</pressure><pressure_string>Higher</pressure_string><abs_humidity>--</abs_humidity><wind_speed>2</wind_speed><wind_direction>E</wind_direction><atmo_opacity>Sunny</atmo_opacity><season>Month 6</season><ls>169.1</ls><sunrise>6 am</sunrise><sunset>5 pm</sunset></magnitudes></record><record><sol>34</sol><terrestrial_date>Sept 10, 2012 UTC</terrestrial_date><magnitudes><min_temp>-75</min_temp><max_temp>0</max_temp><pressure>7.48</pressure><pressure_string>Lower</pressure_string><abs_humidity>--</abs_humidity><wind_speed>2</wind_speed><wind_direction>E</wind_direction><atmo_opacity>Sunny</atmo_opacity><season>Month 6</season><ls>169.5</ls><sunrise>6 am</sunrise><sunset>5 pm</sunset></magnitudes></record><record><sol>35</sol><terrestrial_date>Sept 11, 2012 UTC</terrestrial_date><magnitudes><min_temp>-73</min_temp><max_temp>-2</max_temp><pressure>7.99</pressure><pressure_string>Upper</pressure_string><abs_humidity>--</abs_humidity><wind_speed>2</wind_speed><wind_direction>E</wind_direction><atmo_opacity>Sunny</atmo_opacity><season>Month 6</season><ls>170.2</ls><sunrise>6 am</sunrise><sunset>5 pm</sunset></magnitudes></record><record><sol>35</sol><terrestrial_date>Sept 12, 2012 UTC</terrestrial_date><magnitudes><min_temp>-73</min_temp><max_temp>5</max_temp><pressure>7.44</pressure><pressure_string>Lower</pressure_string><abs_humidity>--</abs_humidity><wind_speed>2</wind_speed><wind_direction>E</wind_direction><atmo_opacity>Sunny</atmo_opacity><season>Month 6</season><ls>170.6</ls><sunrise>6 am</sunrise><sunset>5 pm</sunset></magnitudes></record><record><sol>37</sol><terrestrial_date>Sept 13, 2012 UTC</terrestrial_date><magnitudes><min_temp>-73</min_temp><max_temp>0</max_temp><pressure>7.52</pressure><pressure_string>Lower</pressure_string><abs_humidity>--</abs_humidity><wind_speed>2</wind_speed><wind_direction>E</wind_direction><atmo_opacity>Sunny</atmo_opacity><season>Month 6</season><ls>171.2</ls><sunrise>6 am</sunrise><sunset>5 pm</sunset></magnitudes></record><record><sol>38</sol><terrestrial_date>Sept 14, 2012 UTC</terrestrial_date><magnitudes><min_temp>-73</min_temp><max_temp>3</max_temp><pressure>7.48</pressure><pressure_string>Lower</pressure_string><abs_humidity>--</abs_humidity><wind_speed>2</wind_speed><wind_direction>E</wind_direction><atmo_opacity>Sunny</atmo_opacity><season>month 6</season><ls>171.3</ls><sunrise>6 am</sunrise><sunset>5 pm</sunset></magnitudes></record><record><sol>39</sol><terrestrial_date>Sept 15, 2012 UTC</terrestrial_date><magnitudes><min_temp>-75</min_temp><max_temp>3</max_temp><pressure>7.57</pressure><pressure_string>Lower</pressure_string><abs_humidity>--</abs_humidity><wind_speed>2</wind_speed><wind_direction>E</wind_direction><atmo_opacity>Sunny</atmo_opacity><season>Month 6</season><ls>171.7</ls><sunrise>6 am</sunrise><sunset>5 pm</sunset></magnitudes></record><record><sol>40</sol><terrestrial_date>Sept 16, 2012 UTC</terrestrial_date><magnitudes><min_temp>-75</min_temp><max_temp>2</max_temp><pressure>8.04</pressure><pressure_string>Higher</pressure_string><abs_humidity>--</abs_humidity><wind_speed>2</wind_speed><wind_direction>E</wind_direction><atmo_opacity>Sunny</atmo_opacity><season>Month 6</season><ls>172.8</ls><sunrise>6 am</sunrise><sunset>5 pm</sunset></magnitudes></record><record><sol>41</sol><terrestrial_date>Sept 17, 2012 UTC</terrestrial_date><magnitudes><min_temp>-75</min_temp><max_temp>2</max_temp><pressure>7.52</pressure><pressure_string>Lower</pressure_string><abs_humidity>--</abs_humidity><wind_speed>2</wind_speed><wind_direction>E</wind_direction><atmo_opacity>Sunny</atmo_opacity><season>Month 6</season><ls>173.4</ls><sunrise>6 am</sunrise><sunset>5 pm</sunset></magnitudes></record><record><sol>42</sol><terrestrial_date>Sept 18, 2012 UTC</terrestrial_date><magnitudes><min_temp>-75</min_temp><max_temp>5</max_temp><pressure>7.55</pressure><pressure_string>Lower</pressure_string><abs_humidity>--</abs_humidity><wind_speed>2</wind_speed><wind_direction>E</wind_direction><atmo_opacity>Sunny</atmo_opacity><season>Month 6</season><ls>173.9</ls><sunrise>6 am</sunrise><sunset>5 pm</sunset></magnitudes></record><record><sol>43</sol><terrestrial_date>Sept 19, 2012 UTC</terrestrial_date><magnitudes><min_temp>-73</min_temp><max_temp>3</max_temp><pressure>7.56</pressure><pressure_string>Lower</pressure_string><abs_humidity>--</abs_humidity><wind_speed>2</wind_speed><wind_direction>E</wind_direction><atmo_opacity>Sunny</atmo_opacity><season>Month 6</season><ls>174.6</ls><sunrise>6 am</sunrise><sunset>5 pm</sunset></magnitudes></record><record><sol>44</sol><terrestrial_date>Sept. 20, 2012 UTC</terrestrial_date><magnitudes><min_temp>-75</min_temp><max_temp>3.9</max_temp><pressure>7.54</pressure><pressure_string>Higher</pressure_string><abs_humidity>--</abs_humidity><wind_speed>2</wind_speed><wind_direction>E</wind_direction><atmo_opacity>Sunny</atmo_opacity><season>Month 6</season><ls>175</ls><sunrise>6 am</sunrise><sunset>5 pm</sunset></magnitudes></record><record><sol>45</sol><terrestrial_date>Sept. 21, 2012 UTC</terrestrial_date><magnitudes><min_temp>-74</min_temp><max_temp>2.9</max_temp><pressure>7.57</pressure><pressure_string>Higher</pressure_string><abs_humidity>--</abs_humidity><wind_speed>2</wind_speed><wind_direction>E</wind_direction><atmo_opacity>Sunny</atmo_opacity><season>Month 6</season><ls>175.6</ls><sunrise>6 am</sunrise><sunset>5 pm</sunset></magnitudes></record><record><sol>46</sol><terrestrial_date>Sept 22, 2012 UTC</terrestrial_date><magnitudes><min_temp>-74</min_temp><max_temp>4</max_temp><pressure>7.59</pressure><pressure_string>Lower</pressure_string><abs_humidity>--</abs_humidity><wind_speed>2</wind_speed><wind_direction>E</wind_direction><atmo_opacity>Sunny</atmo_opacity><season>Month 6</season><ls>176.1</ls><sunrise>6 am</sunrise><sunset>5 pm</sunset></magnitudes></record><record><sol>47</sol><terrestrial_date>Sept 23, 2012 UTC</terrestrial_date><magnitudes><min_temp>-75</min_temp><max_temp>6</max_temp><pressure>7.58</pressure><pressure_string>Lower</pressure_string><abs_humidity>--</abs_humidity><wind_speed>2</wind_speed><wind_direction>E</wind_direction><atmo_opacity>Sunny</atmo_opacity><season>Month 6</season><ls>176.7</ls><sunrise>6 am</sunrise><sunset>5 pm</sunset></magnitudes></record><record><sol>48</sol><terrestrial_date>Sept 24, 2012 UTC</terrestrial_date><magnitudes><min_temp>-75</min_temp><max_temp>4</max_temp><pressure>7.58</pressure><pressure_string>Lower</pressure_string><abs_humidity>--</abs_humidity><wind_speed>2</wind_speed><wind_direction>E</wind_direction><atmo_opacity>Sunny</atmo_opacity><season>Month 6</season><ls>177.3</ls><sunrise>6 am</sunrise><sunset>5 pm</sunset></magnitudes></record><record><sol>49</sol><terrestrial_date>Sept 25, 2012 UTC</terrestrial_date><magnitudes><min_temp>-74</min_temp><max_temp>4.4</max_temp><pressure>7.63</pressure><pressure_string>Higher</pressure_string><abs_humidity>--</abs_humidity><wind_speed>2</wind_speed><wind_direction>E</wind_direction><atmo_opacity>Sunny</atmo_opacity><season>Month 6</season><ls>177.8</ls><sunrise>6 am</sunrise><sunset>5 pm</sunset></magnitudes></record><record><sol>50</sol><terrestrial_date>Sept 26, 2012 UTC</terrestrial_date><magnitudes><min_temp>-72</min_temp><max_temp>0</max_temp><pressure>7.6</pressure><pressure_string>Higher</pressure_string><abs_humidity>--</abs_humidity><wind_speed>2</wind_speed><wind_direction>E</wind_direction><atmo_opacity>Sunny</atmo_opacity><season>Month 6</season><ls>178.4</ls><sunrise>6 am</sunrise><sunset>5 pm</sunset></magnitudes></record><record><sol>51</sol><terrestrial_date>Sept 27, 2012 UTC</terrestrial_date><magnitudes><min_temp>-76</min_temp><max_temp>2.5</max_temp><pressure>7.66</pressure><pressure_string>Higher</pressure_string><abs_humidity>--</abs_humidity><wind_speed>2</wind_speed><wind_direction>E</wind_direction><atmo_opacity>Sunny</atmo_opacity><season>Month 6</season><ls>178.9</ls><sunrise>6 am</sunrise><sunset>5 pm</sunset></magnitudes></record><record><sol>52</sol><terrestrial_date>Sept 28, 2012 UTC</terrestrial_date><magnitudes><min_temp>-74</min_temp><max_temp>7</max_temp><pressure>7.65</pressure><pressure_string>Higher</pressure_string><abs_humidity>--</abs_humidity><wind_speed>2</wind_speed><wind_direction>E</wind_direction><atmo_opacity>Sunny</atmo_opacity><season>Month 6</season><ls>178.9</ls><sunrise>6 am</sunrise><sunset>5 pm</sunset></magnitudes></record><record><sol>53</sol><terrestrial_date>Sept 29, 2012 UTC</terrestrial_date><magnitudes><min_temp>-71</min_temp><max_temp>4.8</max_temp><pressure>7.646</pressure><pressure_string>Higher</pressure_string><abs_humidity>--</abs_humidity><wind_speed>2</wind_speed><wind_direction>E</wind_direction><atmo_opacity>Sunny</atmo_opacity><season>Month 7</season><ls>180.1</ls><sunrise>6 am</sunrise><sunset>5 pm</sunset></magnitudes></record><record><sol>54</sol><terrestrial_date>Sept 30, 2012 UTC</terrestrial_date><magnitudes><min_temp>-73</min_temp><max_temp>5</max_temp><pressure>7.64</pressure><pressure_string>Upper</pressure_string><abs_humidity>--</abs_humidity><wind_speed>2</wind_speed><wind_direction>E</wind_direction><atmo_opacity>Sunny</atmo_opacity><season>Month 7</season><ls>181.2</ls><sunrise>6 am</sunrise><sunset>5 pm</sunset></magnitudes></record><record><sol>55</sol><terrestrial_date>Oct 1, 2012 UTC</terrestrial_date><magnitudes><min_temp>-74</min_temp><max_temp>-1</max_temp><pressure>7.68</pressure><pressure_string>Higher</pressure_string><abs_humidity>--</abs_humidity><wind_speed>2</wind_speed><wind_direction>E</wind_direction><atmo_opacity>Sunny</atmo_opacity><season>Month 7</season><ls>180.6</ls><sunrise>6 am</sunrise><sunset>5 pm</sunset></magnitudes></record><record><sol>56</sol><terrestrial_date>Oct 2, 2012 UTC</terrestrial_date><magnitudes><min_temp>-73.5</min_temp><max_temp>-3.8</max_temp><pressure>7.7</pressure><pressure_string>Higher</pressure_string><abs_humidity>--</abs_humidity><wind_speed>2</wind_speed><wind_direction>E</wind_direction><atmo_opacity>Sunny</atmo_opacity><season>Month 7</season><ls>181.8</ls><sunrise>5:31 am</sunrise><sunset>05:09 pm</sunset></magnitudes></record><record><sol>57</sol><terrestrial_date>Oct 3, 2012 UTC</terrestrial_date><magnitudes><min_temp>-73</min_temp><max_temp>-3</max_temp><pressure>7.79</pressure><pressure_string>Higher</pressure_string><abs_humidity>--</abs_humidity><wind_speed>2</wind_speed><wind_direction>E</wind_direction><atmo_opacity>Sunny</atmo_opacity><season>Month 7</season><ls>181.8</ls><sunrise>6 am</sunrise><sunset>5 pm</sunset></magnitudes></record><record><sol>58</sol><terrestrial_date>Oct 4, 2012 UTC</terrestrial_date><magnitudes><min_temp>-74</min_temp><max_temp>-3</max_temp><pressure>7.79</pressure><pressure_string>Higher</pressure_string><abs_humidity>--</abs_humidity><wind_speed>2</wind_speed><wind_direction>E</wind_direction><atmo_opacity>Sunny</atmo_opacity><season>Month 7</season><ls>182.3</ls><sunrise>6 am</sunrise><sunset>5 pm</sunset></magnitudes></record><record><sol>59</sol><terrestrial_date>Oct 5, 2012 UTC</terrestrial_date><magnitudes><min_temp>-76</min_temp><max_temp>-1</max_temp><pressure>7.81</pressure><pressure_string>Higher</pressure_string><abs_humidity>--</abs_humidity><wind_speed>2</wind_speed><wind_direction>E</wind_direction><atmo_opacity>Sunny</atmo_opacity><season>Month 7</season><ls>182.9</ls><sunrise>6 am</sunrise><sunset>5 pm</sunset></magnitudes></record><record><sol>60</sol><terrestrial_date>Oct 6, 2012 UTC</terrestrial_date><magnitudes><min_temp>-75</min_temp><max_temp>-2</max_temp><pressure>7.85</pressure><pressure_string>Higher</pressure_string><abs_humidity>--</abs_humidity><wind_speed>2</wind_speed><wind_direction>E</wind_direction><atmo_opacity>Sunny</atmo_opacity><season>Month 7</season><ls>183.5</ls><sunrise>6 am</sunrise><sunset>5 pm</sunset></magnitudes></record><record><sol>61</sol><terrestrial_date>Oct 7, 2012 UTC</terrestrial_date><magnitudes><min_temp>-72</min_temp><max_temp>-1</max_temp><pressure>7.79</pressure><pressure_string>Higher</pressure_string><abs_humidity>--</abs_humidity><wind_speed>2</wind_speed><wind_direction>E</wind_direction><atmo_opacity>Sunny</atmo_opacity><season>Month 7</season><ls>184</ls><sunrise>6 am</sunrise><sunset>5 pm</sunset></magnitudes></record><record><sol>62</sol><terrestrial_date>Oct 8, 2012 UTC</terrestrial_date><magnitudes><min_temp>-72</min_temp><max_temp>-1</max_temp><pressure>7.82</pressure><pressure_string>Higher</pressure_string><abs_humidity>--</abs_humidity><wind_speed>2</wind_speed><wind_direction>E</wind_direction><atmo_opacity>Sunny</atmo_opacity><season>Month 7</season><ls>184</ls><sunrise>6 am</sunrise><sunset>5 pm</sunset></magnitudes></record><record><sol>63</sol><terrestrial_date>Oct 9, 2012 UTC</terrestrial_date><magnitudes><min_temp>-74</min_temp><max_temp>-1</max_temp><pressure>7.86</pressure><pressure_string>Higher</pressure_string><abs_humidity>--</abs_humidity><wind_speed>2</wind_speed><wind_direction>E</wind_direction><atmo_opacity>Sunny</atmo_opacity><season>Month 7</season><ls>185.5</ls><sunrise>6 am</sunrise><sunset>5 pm</sunset></magnitudes></record><record><sol>64</sol><terrestrial_date>Oct 10, 2012 UTC</terrestrial_date><magnitudes><min_temp>-74</min_temp><max_temp>-1</max_temp><pressure>7.85</pressure><pressure_string>Higher</pressure_string><abs_humidity>--</abs_humidity><wind_speed>2</wind_speed><wind_direction>E</wind_direction><atmo_opacity>Sunny</atmo_opacity><season>Month 7</season><ls>185.8</ls><sunrise>6 am</sunrise><sunset>5 pm</sunset></magnitudes></record><record><sol>65</sol><terrestrial_date>Oct 11, 2012 UTC</terrestrial_date><magnitudes><min_temp>-72</min_temp><max_temp>-2</max_temp><pressure>7.85</pressure><pressure_string>Higher</pressure_string><abs_humidity>--</abs_humidity><wind_speed>2</wind_speed><wind_direction>E</wind_direction><atmo_opacity>Sunny</atmo_opacity><season>Month 7</season><ls>186.3</ls><sunrise>6 am</sunrise><sunset>5 pm</sunset></magnitudes></record><record><sol>66</sol><terrestrial_date>Oct 11, 2012 UTC</terrestrial_date><magnitudes><min_temp>-73</min_temp><max_temp>-2</max_temp><pressure>7.85</pressure><pressure_string>Higher</pressure_string><abs_humidity>--</abs_humidity><wind_speed>2</wind_speed><wind_direction>E</wind_direction><atmo_opacity>Sunny</atmo_opacity><season>Month 7</season><ls>186.9</ls><sunrise>6 am</sunrise><sunset>5 pm</sunset></magnitudes></record><record><sol>67</sol><terrestrial_date>Oct 13, 2012 UTC</terrestrial_date><magnitudes><min_temp>-73</min_temp><max_temp>-5</max_temp><pressure>7.81</pressure><pressure_string>Higher</pressure_string><abs_humidity>--</abs_humidity><wind_speed>2</wind_speed><wind_direction>E</wind_direction><atmo_opacity>Sunny</atmo_opacity><season>Month 7</season><ls>187</ls><sunrise>6 am</sunrise><sunset>5 pm</sunset></magnitudes></record><record><sol>68</sol><terrestrial_date>Oct 14, 2012 UTC</terrestrial_date><magnitudes><min_temp>-68</min_temp><max_temp>-1</max_temp><pressure>--</pressure><pressure_string>--</pressure_string><abs_humidity>--</abs_humidity><wind_speed>2</wind_speed><wind_direction>E</wind_direction><atmo_opacity>Sunny</atmo_opacity><season>Month 7</season><ls>188</ls><sunrise>6 am</sunrise><sunset>5 pm</sunset></magnitudes></record><record><sol>70</sol><terrestrial_date>Oct 16, 2012 UTC</terrestrial_date><magnitudes><min_temp>-72</min_temp><max_temp>1</max_temp><pressure>7.83</pressure><pressure_string>Higher</pressure_string><abs_humidity>--</abs_humidity><wind_speed>2</wind_speed><wind_direction>E</wind_direction><atmo_opacity>Sunny</atmo_opacity><season>Month 7</season><ls>189</ls><sunrise>6 am</sunrise><sunset>5 pm</sunset></magnitudes></record><record><sol>71</sol><terrestrial_date>Oct 17, 2012 UTC</terrestrial_date><magnitudes><min_temp>-71</min_temp><max_temp>-2</max_temp><pressure>7.85</pressure><pressure_string>Higher</pressure_string><abs_humidity>--</abs_humidity><wind_speed>2</wind_speed><wind_direction>E</wind_direction><atmo_opacity>Sunny</atmo_opacity><season>Month 7</season><ls>191</ls><sunrise>6 am</sunrise><sunset>5 pm</sunset></magnitudes></record><record><sol>72</sol><terrestrial_date>Oct 18, 2012 UTC</terrestrial_date><magnitudes><min_temp>-74</min_temp><max_temp>-2</max_temp><pressure>7.86</pressure><pressure_string>Higher</pressure_string><abs_humidity>--</abs_humidity><wind_speed>2</wind_speed><wind_direction>E</wind_direction><atmo_opacity>Sunny</atmo_opacity><season>Month 7</season><ls>192</ls><sunrise>6 am</sunrise><sunset>5 pm</sunset></magnitudes></record><record><sol>73</sol><terrestrial_date>Oct 19, 2012 UTC</terrestrial_date><magnitudes><min_temp>0</min_temp><max_temp>-70</max_temp><pressure>7.88</pressure><pressure_string>Higher</pressure_string><abs_humidity>--</abs_humidity><wind_speed>2</wind_speed><wind_direction>E</wind_direction><atmo_opacity>Sunny</atmo_opacity><season>Month 7</season><ls>191</ls><sunrise>6 am</sunrise><sunset>5 pm</sunset></magnitudes></record><record><sol>74</sol><terrestrial_date>Oct 20, 2012 UTC</terrestrial_date><magnitudes><min_temp>-72</min_temp><max_temp>-5</max_temp><pressure>7.9</pressure><pressure_string>Higher</pressure_string><abs_humidity>--</abs_humidity><wind_speed>2</wind_speed><wind_direction>E</wind_direction><atmo_opacity>Sunny</atmo_opacity><season>Month 7</season><ls>191</ls><sunrise>6 am</sunrise><sunset>5 pm</sunset></magnitudes></record><record><sol>75</sol><terrestrial_date>Oct 22, 2012 UTC</terrestrial_date><magnitudes><min_temp>-73</min_temp><max_temp>-1</max_temp><pressure>7.91</pressure><pressure_string>Higher</pressure_string><abs_humidity>--</abs_humidity><wind_speed>2</wind_speed><wind_direction>E</wind_direction><atmo_opacity>Sunny</atmo_opacity><season>Month 7</season><ls>193</ls><sunrise>6 am</sunrise><sunset>5 pm</sunset></magnitudes></record><record><sol>76</sol><terrestrial_date>Oct 23, 2012 UTC</terrestrial_date><magnitudes><min_temp>-72</min_temp><max_temp>-1</max_temp><pressure>7.91</pressure><pressure_string>Higher</pressure_string><abs_humidity>--</abs_humidity><wind_speed>2</wind_speed><wind_direction>E</wind_direction><atmo_opacity>Sunny</atmo_opacity><season>Month 7</season><ls>193.9</ls><sunrise>6 am</sunrise><sunset>5 pm</sunset></magnitudes></record><record><sol>77</sol><terrestrial_date>Oct 24, 2012 UTC</terrestrial_date><magnitudes><min_temp>-72</min_temp><max_temp>-1</max_temp><pressure>7.93</pressure><pressure_string>Higher</pressure_string><abs_humidity>--</abs_humidity><wind_speed>2</wind_speed><wind_direction>E</wind_direction><atmo_opacity>Sunny</atmo_opacity><season>Month 7</season><ls>193.9</ls><sunrise>6 am</sunrise><sunset>5 pm</sunset></magnitudes></record><record><sol>78</sol><terrestrial_date>Oct 25, 2012 UTC</terrestrial_date><magnitudes><min_temp>-71</min_temp><max_temp>0</max_temp><pressure>7.94</pressure><pressure_string>Higher</pressure_string><abs_humidity>--</abs_humidity><wind_speed>2</wind_speed><wind_direction>E</wind_direction><atmo_opacity>Sunny</atmo_opacity><season>Month 7</season><ls>194.5</ls><sunrise>6 am</sunrise><sunset>5 pm</sunset></magnitudes></record><record><sol>79</sol><terrestrial_date>Oct 26, 2012 UTC</terrestrial_date><magnitudes><min_temp>-73</min_temp><max_temp>-2</max_temp><pressure>7.955</pressure><pressure_string>Higher</pressure_string><abs_humidity>--</abs_humidity><wind_speed>2</wind_speed><wind_direction>E</wind_direction><atmo_opacity>Sunny</atmo_opacity><season>Month 7</season><ls>195</ls><sunrise>6 am</sunrise><sunset>5 pm</sunset></magnitudes></record><record><sol>80</sol><terrestrial_date>Oct 27, 2012 UTC</terrestrial_date><magnitudes><min_temp>-73</min_temp><max_temp>-1</max_temp><pressure>7.97</pressure><pressure_string>Higher</pressure_string><abs_humidity>--</abs_humidity><wind_speed>2</wind_speed><wind_direction>E</wind_direction><atmo_opacity>Sunny</atmo_opacity><season>Month 7</season><ls>195.6</ls><sunrise>6 am</sunrise><sunset>5 pm</sunset></magnitudes></record><record><sol>81</sol><terrestrial_date>Oct 28, 2012 UTC</terrestrial_date><magnitudes><min_temp>-72</min_temp><max_temp>-1.5</max_temp><pressure>7.99</pressure><pressure_string>Higher</pressure_string><abs_humidity>--</abs_humidity><wind_speed>2</wind_speed><wind_direction>E</wind_direction><atmo_opacity>Sunny</atmo_opacity><season>Month 7</season><ls>196.8</ls><sunrise>6 am</sunrise><sunset>5 pm</sunset></magnitudes></record><record><sol>82</sol><terrestrial_date>Oct 29, 2012 UTC</terrestrial_date><magnitudes><min_temp>-72</min_temp><max_temp>-0.4</max_temp><pressure>7.98</pressure><pressure_string>Higher</pressure_string><abs_humidity>--</abs_humidity><wind_speed>2</wind_speed><wind_direction>E</wind_direction><atmo_opacity>Sunny</atmo_opacity><season>Month 7</season><ls>197.4</ls><sunrise>6 am</sunrise><sunset>5 pm</sunset></magnitudes></record><record><sol>83</sol><terrestrial_date>Oct 30, 2012 UTC</terrestrial_date><magnitudes><min_temp>-72.5</min_temp><max_temp>-0.5</max_temp><pressure>8.0051</pressure><pressure_string>Higher</pressure_string><abs_humidity>--</abs_humidity><wind_speed>2</wind_speed><wind_direction>E</wind_direction><atmo_opacity>Sunny</atmo_opacity><season>Month 7</season><ls>198</ls><sunrise>6 am</sunrise><sunset>5 pm</sunset></magnitudes></record><record><sol>84</sol><terrestrial_date>Oct 31, 2012 UTC</terrestrial_date><magnitudes><min_temp>-70</min_temp><max_temp>-0.5</max_temp><pressure>8.04</pressure><pressure_string>Higher</pressure_string><abs_humidity>--</abs_humidity><wind_speed>2</wind_speed><wind_direction>E</wind_direction><atmo_opacity>Sunny</atmo_opacity><season>Month 7</season><ls>198.6</ls><sunrise>6 am</sunrise><sunset>5 pm</sunset></magnitudes></record><record><sol>85</sol><terrestrial_date>Nov 1, 2012 UTC</terrestrial_date><magnitudes><min_temp>-71.4</min_temp><max_temp>-0.9</max_temp><pressure>8.05</pressure><pressure_string>Higher</pressure_string><abs_humidity>--</abs_humidity><wind_speed>2</wind_speed><wind_direction>E</wind_direction><atmo_opacity>Sunny</atmo_opacity><season>Month 7</season><ls>199.2</ls><sunrise>6 am</sunrise><sunset>5 pm</sunset></magnitudes></record><record><sol>86</sol><terrestrial_date>Nov 2, 2012 UTC</terrestrial_date><magnitudes><min_temp>-71</min_temp><max_temp>-4</max_temp><pressure>8.08</pressure><pressure_string>Higher</pressure_string><abs_humidity>--</abs_humidity><wind_speed>2</wind_speed><wind_direction>E</wind_direction><atmo_opacity>Sunny</atmo_opacity><season>Month 7</season><ls>199</ls><sunrise>6 am</sunrise><sunset>5 pm</sunset></magnitudes></record><record><sol>87</sol><terrestrial_date>Nov 3, 2012 UTC</terrestrial_date><magnitudes><min_temp>-70</min_temp><max_temp>-2</max_temp><pressure>8.087</pressure><pressure_string>Higher</pressure_string><abs_humidity>--</abs_humidity><wind_speed>2</wind_speed><wind_direction>E</wind_direction><atmo_opacity>Sunny</atmo_opacity><season>Month 7</season><ls>199.8</ls><sunrise>6 am</sunrise><sunset>5 pm</sunset></magnitudes></record><record><sol>89</sol><terrestrial_date>Nov 5, 2012 UTC</terrestrial_date><magnitudes><min_temp>-73</min_temp><max_temp>-1</max_temp><pressure>8.1335</pressure><pressure_string>Higher</pressure_string><abs_humidity>--</abs_humidity><wind_speed>2</wind_speed><wind_direction>E</wind_direction><atmo_opacity>Sunny</atmo_opacity><season>Month 7</season><ls>201.6</ls><sunrise>6 am</sunrise><sunset>5 pm</sunset></magnitudes></record><record><sol>90</sol><terrestrial_date>Nov 6, 2012 UTC</terrestrial_date><magnitudes><min_temp>-71.2</min_temp><max_temp>-0.4</max_temp><pressure>8.14</pressure><pressure_string>Higher</pressure_string><abs_humidity>--</abs_humidity><wind_speed>2</wind_speed><wind_direction>E</wind_direction><atmo_opacity>Sunny</atmo_opacity><season>Month 7</season><ls>201.6</ls><sunrise>6 am</sunrise><sunset>5 pm</sunset></magnitudes></record><record><sol>91</sol><terrestrial_date>Nov 7, 2012 UTC</terrestrial_date><magnitudes><min_temp>-73.8</min_temp><max_temp>-0.8</max_temp><pressure>8.18</pressure><pressure_string>Higher</pressure_string><abs_humidity>--</abs_humidity><wind_speed>2</wind_speed><wind_direction>E</wind_direction><atmo_opacity>Sunny</atmo_opacity><season>Month 7</season><ls>202.2</ls><sunrise>6 am</sunrise><sunset>5 pm</sunset></magnitudes></record><record><sol>92</sol><terrestrial_date>Nov 8, 2012 UTC</terrestrial_date><magnitudes><min_temp>-74</min_temp><max_temp>0</max_temp><pressure>8.2029</pressure><pressure_string>Higher</pressure_string><abs_humidity>--</abs_humidity><wind_speed>2</wind_speed><wind_direction>E</wind_direction><atmo_opacity>Sunny</atmo_opacity><season>Month 7</season><ls>201.8</ls><sunrise>6 am</sunrise><sunset>5 pm</sunset></magnitudes></record><record><sol>89</sol><terrestrial_date>Nov 10, 2012 UTC</terrestrial_date><magnitudes><min_temp>-71</min_temp><max_temp>0</max_temp><pressure>8.2243</pressure><pressure_string>Higher</pressure_string><abs_humidity>--</abs_humidity><wind_speed>2</wind_speed><wind_direction>E</wind_direction><atmo_opacity>Sunny</atmo_opacity><season>Month 7</season><ls>205.2</ls><sunrise>6 am</sunrise><sunset>5 pm</sunset></magnitudes></record><record><sol>89</sol><terrestrial_date>Nov 11, 2012 UTC</terrestrial_date><magnitudes><min_temp>-71</min_temp><max_temp>0</max_temp><pressure>8.1553</pressure><pressure_string>Higher</pressure_string><abs_humidity>--</abs_humidity><wind_speed>2</wind_speed><wind_direction>E</wind_direction><atmo_opacity>Sunny</atmo_opacity><season>Month 7</season><ls>205.2</ls><sunrise>6 am</sunrise><sunset>5 pm</sunset></magnitudes></record><record><sol>96</sol><terrestrial_date>Nov 12, 2012 UTC</terrestrial_date><magnitudes><min_temp>-70</min_temp><max_temp>2</max_temp><pressure>8.27</pressure><pressure_string>Higher</pressure_string><abs_humidity>--</abs_humidity><wind_speed>2</wind_speed><wind_direction>E</wind_direction><atmo_opacity>Sunny</atmo_opacity><season>Month 7</season><ls>205</ls><sunrise>6 am</sunrise><sunset>5 pm</sunset></magnitudes></record><record><sol>97</sol><terrestrial_date>Nov 13, 2012 UTC</terrestrial_date><magnitudes><min_temp>-68</min_temp><max_temp>-3</max_temp><pressure>8.28</pressure><pressure_string>Higher</pressure_string><abs_humidity>--</abs_humidity><wind_speed>2</wind_speed><wind_direction>E</wind_direction><atmo_opacity>Sunny</atmo_opacity><season>Month 7</season><ls>205</ls><sunrise>6 am</sunrise><sunset>5 pm</sunset></magnitudes></record><record><sol>98</sol><terrestrial_date>Nov 14, 2012 UTC</terrestrial_date><magnitudes><min_temp>-68</min_temp><max_temp>-1</max_temp><pressure>8.29</pressure><pressure_string>Higher</pressure_string><abs_humidity>--</abs_humidity><wind_speed>2</wind_speed><wind_direction>E</wind_direction><atmo_opacity>Sunny</atmo_opacity><season>Month 7</season><ls>206</ls><sunrise>6 am</sunrise><sunset>5 pm</sunset></magnitudes></record><record><sol>98</sol><terrestrial_date>Nov 14, 2012 UTC</terrestrial_date><magnitudes><min_temp>-68</min_temp><max_temp>-1</max_temp><pressure>8.29</pressure><pressure_string>Higher</pressure_string><abs_humidity>--</abs_humidity><wind_speed>2</wind_speed><wind_direction>E</wind_direction><atmo_opacity>Sunny</atmo_opacity><season>Month 7</season><ls>206</ls><sunrise>6 am</sunrise><sunset>5 pm</sunset></magnitudes></record><record><sol>99</sol><terrestrial_date>Nov 15, 2012 UTC</terrestrial_date><magnitudes><min_temp>-68</min_temp><max_temp>-1</max_temp><pressure>8.2959</pressure><pressure_string>Higher</pressure_string><abs_humidity>--</abs_humidity><wind_speed>2</wind_speed><wind_direction>E</wind_direction><atmo_opacity>Sunny</atmo_opacity><season>Month 7</season><ls>207.1</ls><sunrise>6 am</sunrise><sunset>5 pm</sunset></magnitudes></record><record><sol>102</sol><terrestrial_date>Nov 18, 2012 UTC</terrestrial_date><magnitudes><min_temp>-67</min_temp><max_temp>8</max_temp><pressure>8.3341</pressure><pressure_string>Higher</pressure_string><abs_humidity>--</abs_humidity><wind_speed>2</wind_speed><wind_direction>E</wind_direction><atmo_opacity>Sunny</atmo_opacity><season>Month 7</season><ls>208.8</ls><sunrise>6 am</sunrise><sunset>5 pm</sunset></magnitudes></record><record><sol>104</sol><terrestrial_date>Nov 20, 2012 UTC</terrestrial_date><magnitudes><min_temp>-67</min_temp><max_temp>4.7</max_temp><pressure>8.39</pressure><pressure_string>Higher</pressure_string><abs_humidity>--</abs_humidity><wind_speed>2</wind_speed><wind_direction>E</wind_direction><atmo_opacity>Sunny</atmo_opacity><season>Month 8</season><ls>210</ls><sunrise>6 am</sunrise><sunset>5 pm</sunset></magnitudes></record><record><sol>108</sol><terrestrial_date>Nov 25, 2012 UTC</terrestrial_date><magnitudes><min_temp>-65</min_temp><max_temp>5</max_temp><pressure>8.47</pressure><pressure_string>Higher</pressure_string><abs_humidity>--</abs_humidity><wind_speed>2</wind_speed><wind_direction>E</wind_direction><atmo_opacity>Sunny</atmo_opacity><season>Month 8</season><ls>212</ls><sunrise>6 am</sunrise><sunset>5 pm</sunset></magnitudes></record><record><sol>111</sol><terrestrial_date>Nov 29, 2012 UTC</terrestrial_date><magnitudes><min_temp>-66</min_temp><max_temp>5</max_temp><pressure>8.5</pressure><pressure_string>Higher</pressure_string><abs_humidity>--</abs_humidity><wind_speed>2</wind_speed><wind_direction>E</wind_direction><atmo_opacity>Sunny</atmo_opacity><season>Month 8</season><ls>216</ls><sunrise>6 am</sunrise><sunset>5 pm</sunset></magnitudes></record><record><sol>112</sol><terrestrial_date>Nov 30, 2012 UTC</terrestrial_date><magnitudes><min_temp>-66</min_temp><max_temp>2.85</max_temp><pressure>8.52</pressure><pressure_string>Higher</pressure_string><abs_humidity>--</abs_humidity><wind_speed>2</wind_speed><wind_direction>E</wind_direction><atmo_opacity>Sunny</atmo_opacity><season>Month 8</season><ls>216</ls><sunrise>6 am</sunrise><sunset>5 pm</sunset></magnitudes></record><record><sol>113</sol><terrestrial_date>Dec 1, 2012 UTC</terrestrial_date><magnitudes><min_temp>-66.11</min_temp><max_temp>3</max_temp><pressure>8.57</pressure><pressure_string>Higher</pressure_string><abs_humidity>--</abs_humidity><wind_speed>2</wind_speed><wind_direction>E</wind_direction><atmo_opacity>Sunny</atmo_opacity><season>Month 8</season><ls>216.7</ls><sunrise>6 am</sunrise><sunset>5 pm</sunset></magnitudes></record><record><sol>114</sol><terrestrial_date>Dec 2, 2012 UTC</terrestrial_date><magnitudes><min_temp>-69</min_temp><max_temp>3</max_temp><pressure>8.58</pressure><pressure_string>Higher</pressure_string><abs_humidity>--</abs_humidity><wind_speed>2</wind_speed><wind_direction>E</wind_direction><atmo_opacity>Sunny</atmo_opacity><season>Month 8</season><ls>217.4</ls><sunrise>6 am</sunrise><sunset>5 pm</sunset></magnitudes></record><record><sol>115</sol><terrestrial_date>Dec 2, 2012 UTC</terrestrial_date><magnitudes><min_temp>-67</min_temp><max_temp>1.3</max_temp><pressure>8.5726</pressure><pressure_string>Higher</pressure_string><abs_humidity>--</abs_humidity><wind_speed>2</wind_speed><wind_direction>E</wind_direction><atmo_opacity>Sunny</atmo_opacity><season>Month 8</season><ls>217.4</ls><sunrise>6 am</sunrise><sunset>5 pm</sunset></magnitudes></record><record><sol>116</sol><terrestrial_date>Dec 3, 2012 UTC</terrestrial_date><magnitudes><min_temp>-67</min_temp><max_temp>5</max_temp><pressure>8.57</pressure><pressure_string>Higher</pressure_string><abs_humidity>--</abs_humidity><wind_speed>2</wind_speed><wind_direction>E</wind_direction><atmo_opacity>Sunny</atmo_opacity><season>Month 8</season><ls>218</ls><sunrise>6 am</sunrise><sunset>5 pm</sunset></magnitudes></record><record><sol>117</sol><terrestrial_date>Dec 4, 2012 UTC</terrestrial_date><magnitudes><min_temp>-66.37</min_temp><max_temp>3.45</max_temp><pressure>8.62</pressure><pressure_string>Higher</pressure_string><abs_humidity>--</abs_humidity><wind_speed>2</wind_speed><wind_direction>E</wind_direction><atmo_opacity>Sunny</atmo_opacity><season>Month 8</season><ls>219.2</ls><sunrise>6 am</sunrise><sunset>5 pm</sunset></magnitudes></record><record><sol>118</sol><terrestrial_date>Dec 5, 2012 UTC</terrestrial_date><magnitudes><min_temp>-65.19</min_temp><max_temp>4.53</max_temp><pressure>8.64</pressure><pressure_string>Higher</pressure_string><abs_humidity>--</abs_humidity><wind_speed>2</wind_speed><wind_direction>E</wind_direction><atmo_opacity>Sunny</atmo_opacity><season>Month 8</season><ls>219.8</ls><sunrise>6 am</sunrise><sunset>5 pm</sunset></magnitudes></record><record><sol>119</sol><terrestrial_date>Dec 6, 2012 UTC</terrestrial_date><magnitudes><min_temp>-66.22</min_temp><max_temp>3.12</max_temp><pressure>8.663</pressure><pressure_string>Higher</pressure_string><abs_humidity>--</abs_humidity><wind_speed>2</wind_speed><wind_direction>E</wind_direction><atmo_opacity>Sunny</atmo_opacity><season>Month 8</season><ls>220.5</ls><sunrise>6 am</sunrise><sunset>5 pm</sunset></magnitudes></record><record><sol>120</sol><terrestrial_date>Dec 7, 2012 UTC</terrestrial_date><magnitudes><min_temp>-66.67</min_temp><max_temp>5.91</max_temp><pressure>8.675</pressure><pressure_string>Higher</pressure_string><abs_humidity>--</abs_humidity><wind_speed>2</wind_speed><wind_direction>E</wind_direction><atmo_opacity>Sunny</atmo_opacity><season>Month 8</season><ls>221.1</ls><sunrise>6 am</sunrise><sunset>5 pm</sunset></magnitudes></record><record><sol>121</sol><terrestrial_date>Dec 8, 2012 UTC</terrestrial_date><magnitudes><min_temp>-64.1</min_temp><max_temp>1.31</max_temp><pressure>8.654</pressure><pressure_string>Higher</pressure_string><abs_humidity>--</abs_humidity><wind_speed>2</wind_speed><wind_direction>E</wind_direction><atmo_opacity>Sunny</atmo_opacity><season>Month 8</season><ls>221.7</ls><sunrise>6 am</sunrise><sunset>5 pm</sunset></magnitudes></record><record><sol>123</sol><terrestrial_date>Dec 10, 2012 UTC</terrestrial_date><magnitudes><min_temp>-65.7</min_temp><max_temp>2.1</max_temp><pressure>8.7596</pressure><pressure_string>Higher</pressure_string><abs_humidity>--</abs_humidity><wind_speed>2</wind_speed><wind_direction>E</wind_direction><atmo_opacity>Sunny</atmo_opacity><season>Month 8</season><ls>222.3</ls><sunrise>6 am</sunrise><sunset>5 pm</sunset></magnitudes></record><record><sol>124</sol><terrestrial_date>Dec 11, 2012 UTC</terrestrial_date><magnitudes><min_temp>-65.5</min_temp><max_temp>5.4</max_temp><pressure>8.7684</pressure><pressure_string>Higher</pressure_string><abs_humidity>--</abs_humidity><wind_speed>2</wind_speed><wind_direction>E</wind_direction><atmo_opacity>Sunny</atmo_opacity><season>Month 8</season><ls>222.9</ls><sunrise>6 am</sunrise><sunset>5 pm</sunset></magnitudes></record><record><sol>125</sol><terrestrial_date>Dec 12, 2012 UTC</terrestrial_date><magnitudes><min_temp>-63.8</min_temp><max_temp>3.4</max_temp><pressure>8.7525</pressure><pressure_string>Higher</pressure_string><abs_humidity>--</abs_humidity><wind_speed>2</wind_speed><wind_direction>E</wind_direction><atmo_opacity>Sunny</atmo_opacity><season>Month 8</season><ls>224.8</ls><sunrise>6 am</sunrise><sunset>5 pm</sunset></magnitudes></record><record><sol>126</sol><terrestrial_date>Dec 13, 2012 UTC</terrestrial_date><magnitudes><min_temp>-67</min_temp><max_temp>-5</max_temp><pressure>8.8</pressure><pressure_string>Higher</pressure_string><abs_humidity>--</abs_humidity><wind_speed>2</wind_speed><wind_direction>E</wind_direction><atmo_opacity>Sunny</atmo_opacity><season>Month 8</season><ls>224.2</ls><sunrise>6 am</sunrise><sunset>5 pm</sunset></magnitudes></record><record><sol>127</sol><terrestrial_date>Dec 14, 2012 UTC</terrestrial_date><magnitudes><min_temp>-67</min_temp><max_temp>2</max_temp><pressure>8.84</pressure><pressure_string>Higher</pressure_string><abs_humidity>--</abs_humidity><wind_speed>2</wind_speed><wind_direction>E</wind_direction><atmo_opacity>Sunny</atmo_opacity><season>Month 8</season><ls>224.8</ls><sunrise>6 am</sunrise><sunset>5 pm</sunset></magnitudes></record><record><sol>128</sol><terrestrial_date>Dec 15, 2012 UTC</terrestrial_date><magnitudes><min_temp>-67</min_temp><max_temp>-4</max_temp><pressure>8.84</pressure><pressure_string>Higher</pressure_string><abs_humidity>--</abs_humidity><wind_speed>2</wind_speed><wind_direction>E</wind_direction><atmo_opacity>Sunny</atmo_opacity><season>Month 8</season><ls>225.4</ls><sunrise>6 am</sunrise><sunset>5 pm</sunset></magnitudes></record><record><sol>129</sol><terrestrial_date>Dec 16, 2012 UTC</terrestrial_date><magnitudes><min_temp>-66</min_temp><max_temp>-4</max_temp><pressure>8.94</pressure><pressure_string>Higher</pressure_string><abs_humidity>--</abs_humidity><wind_speed>2</wind_speed><wind_direction>E</wind_direction><atmo_opacity>Sunny</atmo_opacity><season>Month 8</season><ls>226.1</ls><sunrise>6 am</sunrise><sunset>5 pm</sunset></magnitudes></record><record><sol>130</sol><terrestrial_date>Dec 17, 2012 UTC</terrestrial_date><magnitudes><min_temp>-66</min_temp><max_temp>-6</max_temp><pressure>8.89</pressure><pressure_string>Higher</pressure_string><abs_humidity>--</abs_humidity><wind_speed>2</wind_speed><wind_direction>E</wind_direction><atmo_opacity>Sunny</atmo_opacity><season>Month 8</season><ls>226.7</ls><sunrise>6 am</sunrise><sunset>5 pm</sunset></magnitudes></record><record><sol>131</sol><terrestrial_date>Dec 18, 2012 UTC</terrestrial_date><magnitudes><min_temp>-66</min_temp><max_temp>-7</max_temp><pressure>8.88</pressure><pressure_string>Higher</pressure_string><abs_humidity>--</abs_humidity><wind_speed>2</wind_speed><wind_direction>E</wind_direction><atmo_opacity>Sunny</atmo_opacity><season>Month 8</season><ls>227</ls><sunrise>6 am</sunrise><sunset>5 pm</sunset></magnitudes></record><record><sol>132</sol><terrestrial_date>Dec 19, 2012 UTC</terrestrial_date><magnitudes><min_temp>-65.4</min_temp><max_temp>-6.8</max_temp><pressure>8.9284</pressure><pressure_string>Higher</pressure_string><abs_humidity>--</abs_humidity><wind_speed>2</wind_speed><wind_direction>E</wind_direction><atmo_opacity>Sunny</atmo_opacity><season>Month 8</season><ls>227.9</ls><sunrise>6 am</sunrise><sunset>5 pm</sunset></magnitudes></record><record><sol>133</sol><terrestrial_date>Dec 20, 2012 UTC</terrestrial_date><magnitudes><min_temp>-65.4</min_temp><max_temp>0.6</max_temp><pressure>8.9121</pressure><pressure_string>Higher</pressure_string><abs_humidity>--</abs_humidity><wind_speed>2</wind_speed><wind_direction>E</wind_direction><atmo_opacity>Sunny</atmo_opacity><season>Month 8</season><ls>228.6</ls><sunrise>6 am</sunrise><sunset>5 pm</sunset></magnitudes></record><record><sol>134</sol><terrestrial_date>Dec 21, 2012 UTC</terrestrial_date><magnitudes><min_temp>-66.79</min_temp><max_temp>-0.62</max_temp><pressure>8.9399</pressure><pressure_string>Higher</pressure_string><abs_humidity>--</abs_humidity><wind_speed>2</wind_speed><wind_direction>E</wind_direction><atmo_opacity>Sunny</atmo_opacity><season>Month 8</season><ls>229.2</ls><sunrise>6 am</sunrise><sunset>5 pm</sunset></magnitudes></record><record><sol>135</sol><terrestrial_date>Dec 22, 2012 UTC</terrestrial_date><magnitudes><min_temp>-64.88</min_temp><max_temp>-4.66</max_temp><pressure>8.9434</pressure><pressure_string>Higher</pressure_string><abs_humidity>--</abs_humidity><wind_speed>2</wind_speed><wind_direction>E</wind_direction><atmo_opacity>Sunny</atmo_opacity><season>Month 8</season><ls>229.8</ls><sunrise>6 am</sunrise><sunset>5 pm</sunset></magnitudes></record><record><sol>144</sol><terrestrial_date>31 Dec, 2012 UTC</terrestrial_date><magnitudes><min_temp>-64</min_temp><max_temp>-3</max_temp><pressure>9.07</pressure><pressure_string>Higher</pressure_string><abs_humidity>--</abs_humidity><wind_speed>2</wind_speed><wind_direction>E</wind_direction><atmo_opacity>Sunny</atmo_opacity><season>Month 8</season><ls>235.5</ls><sunrise>6 am</sunrise><sunset>5 pm</sunset></magnitudes></record><record><sol>144</sol><terrestrial_date>1 Dec, 2012 UTC</terrestrial_date><magnitudes><min_temp>-65</min_temp><max_temp>-1</max_temp><pressure>8.51</pressure><pressure_string>Higher</pressure_string><abs_humidity>--</abs_humidity><wind_speed>2</wind_speed><wind_direction>E</wind_direction><atmo_opacity>Sunny</atmo_opacity><season>Month 8</season><ls>236.1</ls><sunrise>6 am</sunrise><sunset>5 pm</sunset></magnitudes></record><record><sol>146</sol><terrestrial_date>2 ene, 2013 UTC</terrestrial_date><magnitudes><min_temp>-65</min_temp><max_temp>-2</max_temp><pressure>9.08</pressure><pressure_string>Higher</pressure_string><abs_humidity>--</abs_humidity><wind_speed>2</wind_speed><wind_direction>E</wind_direction><atmo_opacity>Sunny</atmo_opacity><season>Month 8</season><ls>237.4</ls><sunrise>6 am</sunrise><sunset>5 pm</sunset></magnitudes></record><record><sol>149</sol><terrestrial_date>6 ene, 2013 UTC</terrestrial_date><magnitudes><min_temp>-65</min_temp><max_temp>3</max_temp><pressure>9.14</pressure><pressure_string>Higher</pressure_string><abs_humidity>--</abs_humidity><wind_speed>2</wind_speed><wind_direction>E</wind_direction><atmo_opacity>Sunny</atmo_opacity><season>Month 8</season><ls>239.3</ls><sunrise>6 am</sunrise><sunset>5 pm</sunset></magnitudes></record><record><sol>150</sol><terrestrial_date>7 ene, 2013 UTC</terrestrial_date><magnitudes><min_temp>-64</min_temp><max_temp>2</max_temp><pressure>9.13</pressure><pressure_string>Higher</pressure_string><abs_humidity>--</abs_humidity><wind_speed>2</wind_speed><wind_direction>E</wind_direction><atmo_opacity>Sunny</atmo_opacity><season>Month 8</season><ls>239.9</ls><sunrise>6 am</sunrise><sunset>5 pm</sunset></magnitudes></record><record><sol>150</sol><terrestrial_date>8 ene, 2013 UTC</terrestrial_date><magnitudes><min_temp>-65</min_temp><max_temp>0.5</max_temp><pressure>9.15</pressure><pressure_string>Higher</pressure_string><abs_humidity>--</abs_humidity><wind_speed>2</wind_speed><wind_direction>E</wind_direction><atmo_opacity>Sunny</atmo_opacity><season>Month 9</season><ls>241.2</ls><sunrise>6 am</sunrise><sunset>5 pm</sunset></magnitudes></record><record><sol>152</sol><terrestrial_date>9 ene, 2013 UTC</terrestrial_date><magnitudes><min_temp>-62.55</min_temp><max_temp>3.85</max_temp><pressure>9.145</pressure><pressure_string>Higher</pressure_string><abs_humidity>--</abs_humidity><wind_speed>2</wind_speed><wind_direction>E</wind_direction><atmo_opacity>Sunny</atmo_opacity><season>Month 9</season><ls>241.8</ls><sunrise>6 am</sunrise><sunset>5 pm</sunset></magnitudes></record><record><sol>153</sol><terrestrial_date>10 ene, 2013 UTC</terrestrial_date><magnitudes><min_temp>-65.3</min_temp><max_temp>2.66</max_temp><pressure>9.156</pressure><pressure_string>Higher</pressure_string><abs_humidity>--</abs_humidity><wind_speed>2</wind_speed><wind_direction>E</wind_direction><atmo_opacity>Sunny</atmo_opacity><season>Month 9</season><ls>242.4</ls><sunrise>6 am</sunrise><sunset>5 pm</sunset></magnitudes></record><record><sol>154</sol><terrestrial_date>11 ene, 2013 UTC</terrestrial_date><magnitudes><min_temp>-64.65</min_temp><max_temp>1.45</max_temp><pressure>9.177</pressure><pressure_string>Higher</pressure_string><abs_humidity>--</abs_humidity><wind_speed>2</wind_speed><wind_direction>E</wind_direction><atmo_opacity>Sunny</atmo_opacity><season>Month 9</season><ls>243.1</ls><sunrise>6 am</sunrise><sunset>5 pm</sunset></magnitudes></record><record><sol>155</sol><terrestrial_date>12 ene, 2013 UTC</terrestrial_date><magnitudes><min_temp>-64.45</min_temp><max_temp>2.15</max_temp><pressure>9.175</pressure><pressure_string>Higher</pressure_string><abs_humidity>--</abs_humidity><wind_speed>2</wind_speed><wind_direction>E</wind_direction><atmo_opacity>Sunny</atmo_opacity><season>Month 9</season><ls>243.7</ls><sunrise>6 am</sunrise><sunset>5 pm</sunset></magnitudes></record><record><sol>156</sol><terrestrial_date>Ene 12, 2012 UTC</terrestrial_date><magnitudes><min_temp>-65.31</min_temp><max_temp>1.86</max_temp><pressure>9.177</pressure><pressure_string>Higher</pressure_string><abs_humidity>--</abs_humidity><wind_speed>2</wind_speed><wind_direction>E</wind_direction><atmo_opacity>Sunny</atmo_opacity><season>Month 9</season><ls>243.7</ls><sunrise>6 am</sunrise><sunset>5 pm</sunset></magnitudes></record><record><sol>157</sol><terrestrial_date>Ene 14, 2012 UTC</terrestrial_date><magnitudes><min_temp>-64.42</min_temp><max_temp>1.75</max_temp><pressure>9.207</pressure><pressure_string>Higher</pressure_string><abs_humidity>--</abs_humidity><wind_speed>2</wind_speed><wind_direction>E</wind_direction><atmo_opacity>Sunny</atmo_opacity><season>Month 9</season><ls>244.3</ls><sunrise>6 am</sunrise><sunset>5 pm</sunset></magnitudes></record><record><sol>158</sol><terrestrial_date>Ene 15, 2012 UTC</terrestrial_date><magnitudes><min_temp>-66.47</min_temp><max_temp>2.68</max_temp><pressure>9.2299</pressure><pressure_string>Higher</pressure_string><abs_humidity>--</abs_humidity><wind_speed>2</wind_speed><wind_direction>E</wind_direction><atmo_opacity>Sunny</atmo_opacity><season>Month 9</season><ls>245</ls><sunrise>6 am</sunrise><sunset>5 pm</sunset></magnitudes></record><record><sol>159</sol><terrestrial_date>Ene 16, 2012 UTC</terrestrial_date><magnitudes><min_temp>-65.22</min_temp><max_temp>3.51</max_temp><pressure>9.1847</pressure><pressure_string>Higher</pressure_string><abs_humidity>--</abs_humidity><wind_speed>2</wind_speed><wind_direction>E</wind_direction><atmo_opacity>Sunny</atmo_opacity><season>Month 9</season><ls>245.6</ls><sunrise>6 am</sunrise><sunset>5 pm</sunset></magnitudes></record><record><sol>160</sol><terrestrial_date>Ene 17, 2012 UTC</terrestrial_date><magnitudes><min_temp>-66.69</min_temp><max_temp>-1.98</max_temp><pressure>9.1982</pressure><pressure_string>Higher</pressure_string><abs_humidity>--</abs_humidity><wind_speed>2</wind_speed><wind_direction>E</wind_direction><atmo_opacity>Sunny</atmo_opacity><season>Month 9</season><ls>246.2</ls><sunrise>6 am</sunrise><sunset>5 pm</sunset></magnitudes></record><record><sol>161</sol><terrestrial_date>18 ene, 2013 UTC</terrestrial_date><magnitudes><min_temp>-65</min_temp><max_temp>0</max_temp><pressure>9.203</pressure><pressure_string>Higher</pressure_string><abs_humidity>--</abs_humidity><wind_speed>2</wind_speed><wind_direction>E</wind_direction><atmo_opacity>Sunny</atmo_opacity><season>Month 9</season><ls>246.9</ls><sunrise>6 am</sunrise><sunset>5 pm</sunset></magnitudes></record><record><sol>162</sol><terrestrial_date>19 ene, 2013 UTC</terrestrial_date><magnitudes><min_temp>-65</min_temp><max_temp>1</max_temp><pressure>9.2</pressure><pressure_string>Higher</pressure_string><abs_humidity>--</abs_humidity><wind_speed>2</wind_speed><wind_direction>E</wind_direction><atmo_opacity>Sunny</atmo_opacity><season>Month 9</season><ls>246.9</ls><sunrise>6 am</sunrise><sunset>5 pm</sunset></magnitudes></record><record><sol>163</sol><terrestrial_date>20 ene, 2013 UTC</terrestrial_date><magnitudes><min_temp>-65</min_temp><max_temp>0</max_temp><pressure>9.2</pressure><pressure_string>Higher</pressure_string><abs_humidity>--</abs_humidity><wind_speed>2</wind_speed><wind_direction>E</wind_direction><atmo_opacity>Sunny</atmo_opacity><season>Month 9</season><ls>248.8</ls><sunrise>6 am</sunrise><sunset>5 pm</sunset></magnitudes></record><record><sol>164</sol><terrestrial_date>Ene 21, 2012 UTC</terrestrial_date><magnitudes><min_temp>-64.72</min_temp><max_temp>0,08</max_temp><pressure>9.1946</pressure><pressure_string>Higher</pressure_string><abs_humidity>--</abs_humidity><wind_speed>2</wind_speed><wind_direction>E</wind_direction><atmo_opacity>Sunny</atmo_opacity><season>Month 9</season><ls>248.8</ls><sunrise>6 am</sunrise><sunset>5 pm</sunset></magnitudes></record><record><sol>165</sol><terrestrial_date>Ene 22, 2012 UTC</terrestrial_date><magnitudes><min_temp>-64.66</min_temp><max_temp>-0.1</max_temp><pressure>9.2309</pressure><pressure_string>Higher</pressure_string><abs_humidity>--</abs_humidity><wind_speed>2</wind_speed><wind_direction>E</wind_direction><atmo_opacity>Sunny</atmo_opacity><season>Month 9</season><ls>249.4</ls><sunrise>6 am</sunrise><sunset>5 pm</sunset></magnitudes></record><record><sol>166</sol><terrestrial_date>Jan 23, 2013 UTC</terrestrial_date><magnitudes><min_temp>-65</min_temp><max_temp>3</max_temp><pressure>9.22</pressure><pressure_string>Higher</pressure_string><abs_humidity>--</abs_humidity><wind_speed>2</wind_speed><wind_direction>E</wind_direction><atmo_opacity>Sunny</atmo_opacity><season>Month 9</season><ls>250</ls><sunrise>6 am</sunrise><sunset>5 pm</sunset></magnitudes></record><record><sol>167</sol><terrestrial_date>Jan 24, 2013 UTC</terrestrial_date><magnitudes><min_temp>-65</min_temp><max_temp>4</max_temp><pressure>9.21</pressure><pressure_string>Higher</pressure_string><abs_humidity>--</abs_humidity><wind_speed>2</wind_speed><wind_direction>E</wind_direction><atmo_opacity>Sunny</atmo_opacity><season>Month 9</season><ls>250</ls><sunrise>6 am</sunrise><sunset>5 pm</sunset></magnitudes></record><record><sol>168</sol><terrestrial_date>Jan 25, 2013 UTC</terrestrial_date><magnitudes><min_temp>-66</min_temp><max_temp>5</max_temp><pressure>9.24</pressure><pressure_string>Higher</pressure_string><abs_humidity>--</abs_humidity><wind_speed>2</wind_speed><wind_direction>E</wind_direction><atmo_opacity>Sunny</atmo_opacity><season>Month 9</season><ls>251</ls><sunrise>6 am</sunrise><sunset>5 pm</sunset></magnitudes></record><record><sol>169</sol><terrestrial_date>Jan 26, 2013 UTC</terrestrial_date><magnitudes><min_temp>-66</min_temp><max_temp>4</max_temp><pressure>9.23</pressure><pressure_string>Higher</pressure_string><abs_humidity>--</abs_humidity><wind_speed>2</wind_speed><wind_direction>E</wind_direction><atmo_opacity>Sunny</atmo_opacity><season>Month 9</season><ls>252</ls><sunrise>6 am</sunrise><sunset>5 pm</sunset></magnitudes></record><record><sol>171</sol><terrestrial_date>Jan 29, 2013 UTC</terrestrial_date><magnitudes><min_temp>-66</min_temp><max_temp>6</max_temp><pressure>9.25</pressure><pressure_string>Higher</pressure_string><abs_humidity>--</abs_humidity><wind_speed>2</wind_speed><wind_direction>E</wind_direction><atmo_opacity>Sunny</atmo_opacity><season>Month 9</season><ls>254</ls><sunrise>6 am</sunrise><sunset>5 pm</sunset></magnitudes></record><record><sol>172</sol><terrestrial_date>Jan 30, 2013 UTC</terrestrial_date><magnitudes><min_temp>-66</min_temp><max_temp>6</max_temp><pressure>9.24</pressure><pressure_string>Higher</pressure_string><abs_humidity>--</abs_humidity><wind_speed>2</wind_speed><wind_direction>E</wind_direction><atmo_opacity>Sunny</atmo_opacity><season>Month 9</season><ls>254</ls><sunrise>6 am</sunrise><sunset>5 pm</sunset></magnitudes></record><record><sol>173</sol><terrestrial_date>Jan 31, 2013 UTC</terrestrial_date><magnitudes><min_temp>-66</min_temp><max_temp>5</max_temp><pressure>9.2</pressure><pressure_string>Higher</pressure_string><abs_humidity>--</abs_humidity><wind_speed>2</wind_speed><wind_direction>E</wind_direction><atmo_opacity>Sunny</atmo_opacity><season>Month 9</season><ls>254</ls><sunrise>6 am</sunrise><sunset>5 pm</sunset></magnitudes></record><record><sol>174</sol><terrestrial_date>Jan 31, 2013 UTC</terrestrial_date><magnitudes><min_temp>-67.0</min_temp><max_temp>5.25</max_temp><pressure>9.2447</pressure><pressure_string>Higher</pressure_string><abs_humidity>--</abs_humidity><wind_speed>2</wind_speed><wind_direction>E</wind_direction><atmo_opacity>Sunny</atmo_opacity><season>Month 9</season><ls>255.1</ls><sunrise>6 am</sunrise><sunset>5 pm</sunset></magnitudes></record><record><sol>176</sol><terrestrial_date>Feb 02, 2013 UTC</terrestrial_date><magnitudes><min_temp>-66.7</min_temp><max_temp>5.1</max_temp><pressure>9.1921</pressure><pressure_string>Higher</pressure_string><abs_humidity>--</abs_humidity><wind_speed>2</wind_speed><wind_direction>E</wind_direction><atmo_opacity>Sunny</atmo_opacity><season>Month 9</season><ls>257.1</ls><sunrise>6 am</sunrise><sunset>5 pm</sunset></magnitudes></record><record><sol>177</sol><terrestrial_date>Feb 03, 2013 UTC</terrestrial_date><magnitudes><min_temp>-66.3</min_temp><max_temp>5.2</max_temp><pressure>9.2235</pressure><pressure_string>Higher</pressure_string><abs_humidity>--</abs_humidity><wind_speed>2</wind_speed><wind_direction>E</wind_direction><atmo_opacity>Sunny</atmo_opacity><season>Month 9</season><ls>257.7</ls><sunrise>6 am</sunrise><sunset>5 pm</sunset></magnitudes></record><record><sol>177</sol><terrestrial_date>Feb 04, 2013 UTC</terrestrial_date><magnitudes><min_temp>-65.61</min_temp><max_temp>2.2</max_temp><pressure>9.2131</pressure><pressure_string>Higher</pressure_string><abs_humidity>--</abs_humidity><wind_speed>2</wind_speed><wind_direction>E</wind_direction><atmo_opacity>Sunny</atmo_opacity><season>Month 9</season><ls>258.3</ls><sunrise>6 am</sunrise><sunset>5 pm</sunset></magnitudes></record><record><sol>179</sol><terrestrial_date>Feb 5, 2013 UTC</terrestrial_date><magnitudes><min_temp>-66.25</min_temp><max_temp>4.95</max_temp><pressure>9.2111</pressure><pressure_string>Higher</pressure_string><abs_humidity>--</abs_humidity><wind_speed>2</wind_speed><wind_direction>E</wind_direction><atmo_opacity>Sunny</atmo_opacity><season>Month 9</season><ls>258.3</ls><sunrise>6 am</sunrise><sunset>5 pm</sunset></magnitudes></record><record><sol>180</sol><terrestrial_date>Feb 6, 2013 UTC</terrestrial_date><magnitudes><min_temp>-66.6</min_temp><max_temp>3.9</max_temp><pressure>9.2027</pressure><pressure_string>Higher</pressure_string><abs_humidity>--</abs_humidity><wind_speed>2</wind_speed><wind_direction>E</wind_direction><atmo_opacity>Sunny</atmo_opacity><season>Month 9</season><ls>258.9</ls><sunrise>6 am</sunrise><sunset>5 pm</sunset></magnitudes></record><record><sol>182</sol><terrestrial_date>Feb 8, 2013 UTC</terrestrial_date><magnitudes><min_temp>-67.3</min_temp><max_temp>5.8</max_temp><pressure>9.2196</pressure><pressure_string>Higher</pressure_string><abs_humidity>--</abs_humidity><wind_speed>2</wind_speed><wind_direction>E</wind_direction><atmo_opacity>Sunny</atmo_opacity><season>Month 9</season><ls>260.2</ls><sunrise>6 am</sunrise><sunset>5 pm</sunset></magnitudes></record><record><sol>184</sol><terrestrial_date>10 Feb, 2013 UTC</terrestrial_date><magnitudes><min_temp>-67</min_temp><max_temp>3</max_temp><pressure>9.2</pressure><pressure_string>Higher</pressure_string><abs_humidity>--</abs_humidity><wind_speed>2</wind_speed><wind_direction>E</wind_direction><atmo_opacity>Sunny</atmo_opacity><season>Month 9</season><ls>261.5</ls><sunrise>6 am</sunrise><sunset>5 pm</sunset></magnitudes></record><record><sol>185</sol><terrestrial_date>11 Feb, 2013 UTC</terrestrial_date><magnitudes><min_temp>-68</min_temp><max_temp>4</max_temp><pressure>9.23</pressure><pressure_string>Higher</pressure_string><abs_humidity>--</abs_humidity><wind_speed>2</wind_speed><wind_direction>E</wind_direction><atmo_opacity>Sunny</atmo_opacity><season>Month 9</season><ls>262.1</ls><sunrise>6 am</sunrise><sunset>5 pm</sunset></magnitudes></record><record><sol>186</sol><terrestrial_date>Feb 14, 2013 UTC</terrestrial_date><magnitudes><min_temp>-66</min_temp><max_temp>4</max_temp><pressure>9.22</pressure><pressure_string>Higher</pressure_string><abs_humidity>--</abs_humidity><wind_speed>2</wind_speed><wind_direction>E</wind_direction><atmo_opacity>Sunny</atmo_opacity><season>Month 9</season><ls>264</ls><sunrise>6 am</sunrise><sunset>5 pm</sunset></magnitudes></record><record><sol>187</sol><terrestrial_date>Feb 14, 2013 UTC</terrestrial_date><magnitudes><min_temp>-67</min_temp><max_temp>6</max_temp><pressure>9.22</pressure><pressure_string>Higher</pressure_string><abs_humidity>--</abs_humidity><wind_speed>2</wind_speed><wind_direction>E</wind_direction><atmo_opacity>Sunny</atmo_opacity><season>Month 9</season><ls>264</ls><sunrise>6 am</sunrise><sunset>5 pm</sunset></magnitudes></record><record><sol>188</sol><terrestrial_date>15 Feb, 2013 UTC</terrestrial_date><magnitudes><min_temp>-68</min_temp><max_temp>2</max_temp><pressure>9.205</pressure><pressure_string>Higher</pressure_string><abs_humidity>--</abs_humidity><wind_speed>2</wind_speed><wind_direction>E</wind_direction><atmo_opacity>Sunny</atmo_opacity><season>Month 9</season><ls>264.6</ls><sunrise>6 am</sunrise><sunset>5 pm</sunset></magnitudes></record><record><sol>189</sol><terrestrial_date>Feb 16, 2013 UTC</terrestrial_date><magnitudes><min_temp>-68.3</min_temp><max_temp>-1.4</max_temp><pressure>9.2109</pressure><pressure_string>Higher</pressure_string><abs_humidity>--</abs_humidity><wind_speed>2</wind_speed><wind_direction>E</wind_direction><atmo_opacity>Sunny</atmo_opacity><season>Month 9</season><ls>265.3</ls><sunrise>6 am</sunrise><sunset>5 pm</sunset></magnitudes></record><record><sol>190</sol><terrestrial_date>Feb 17, 2013 UTC</terrestrial_date><magnitudes><min_temp>-67</min_temp><max_temp>-2</max_temp><pressure>9.18</pressure><pressure_string>Higher</pressure_string><abs_humidity>--</abs_humidity><wind_speed>2</wind_speed><wind_direction>E</wind_direction><atmo_opacity>Sunny</atmo_opacity><season>Month 9</season><ls>266</ls><sunrise>6 am</sunrise><sunset>5 pm</sunset></magnitudes></record><record><sol>191</sol><terrestrial_date>Feb 18, 2013 UTC</terrestrial_date><magnitudes><min_temp>-67</min_temp><max_temp>-1</max_temp><pressure>9.21</pressure><pressure_string>Higher</pressure_string><abs_humidity>--</abs_humidity><wind_speed>2</wind_speed><wind_direction>E</wind_direction><atmo_opacity>Sunny</atmo_opacity><season>Month 9</season><ls>266</ls><sunrise>6 am</sunrise><sunset>5 pm</sunset></magnitudes></record><record><sol>191</sol><terrestrial_date>Feb 24, 2013 UTC</terrestrial_date><magnitudes><min_temp>-68</min_temp><max_temp>4.3</max_temp><pressure>9.158</pressure><pressure_string>Higher</pressure_string><abs_humidity>--</abs_humidity><wind_speed>2</wind_speed><wind_direction>E</wind_direction><atmo_opacity>Sunny</atmo_opacity><season>Month 10</season><ls>270.3</ls><sunrise>6 am</sunrise><sunset>5 pm</sunset></magnitudes></record><record><sol>198</sol><terrestrial_date>Feb 24, 2013 UTC</terrestrial_date><magnitudes><min_temp>-67.1</min_temp><max_temp>4.82</max_temp><pressure>9.1434</pressure><pressure_string>Higher</pressure_string><abs_humidity>--</abs_humidity><wind_speed>2</wind_speed><wind_direction>E</wind_direction><atmo_opacity>Sunny</atmo_opacity><season>Month 10</season><ls>271.5</ls><sunrise>6 am</sunrise><sunset>5 pm</sunset></magnitudes></record><record><sol>199</sol><terrestrial_date>Feb 26, 2013 UTC</terrestrial_date><magnitudes><min_temp>-66.16</min_temp><max_temp>6.34</max_temp><pressure>9.1755</pressure><pressure_string>Higher</pressure_string><abs_humidity>--</abs_humidity><wind_speed>2</wind_speed><wind_direction>E</wind_direction><atmo_opacity>Sunny</atmo_opacity><season>Month 10</season><ls>271.5</ls><sunrise>6 am</sunrise><sunset>5 pm</sunset></magnitudes></record><record><sol>222</sol><terrestrial_date>Mar 23, 2013 UTC</terrestrial_date><magnitudes><min_temp>-70</min_temp><max_temp>3</max_temp><pressure>9.18</pressure><pressure_string>Higher</pressure_string><abs_humidity>--</abs_humidity><wind_speed>2</wind_speed><wind_direction>E</wind_direction><atmo_opacity>Sunny</atmo_opacity><season>Month 10</season><ls>287</ls><sunrise>6 am</sunrise><sunset>5 pm</sunset></magnitudes></record><record><sol>224</sol><terrestrial_date>Mar 25, 2013 UTC</terrestrial_date><magnitudes><min_temp>-70</min_temp><max_temp>3</max_temp><pressure>8.94</pressure><pressure_string>Higher</pressure_string><abs_humidity>--</abs_humidity><wind_speed>2</wind_speed><wind_direction>E</wind_direction><atmo_opacity>Sunny</atmo_opacity><season>Month 10</season><ls>288</ls><sunrise>6 am</sunrise><sunset>5 pm</sunset></magnitudes></record><record><sol>225</sol><terrestrial_date>Mar 25, 2013 UTC</terrestrial_date><magnitudes><min_temp>-70.76</min_temp><max_temp>1.27</max_temp><pressure>8.9434</pressure><pressure_string>Higher</pressure_string><abs_humidity>--</abs_humidity><wind_speed>2</wind_speed><wind_direction>E</wind_direction><atmo_opacity>Sunny</atmo_opacity><season>Month 10</season><ls>288.9</ls><sunrise>6 am</sunrise><sunset>5 pm</sunset></magnitudes></record><record><sol>226</sol><terrestrial_date>Mar 26, 2013 UTC</terrestrial_date><magnitudes><min_temp>-69.98</min_temp><max_temp>3.63</max_temp><pressure>8.9465</pressure><pressure_string>Higher</pressure_string><abs_humidity>--</abs_humidity><wind_speed>2</wind_speed><wind_direction>E</wind_direction><atmo_opacity>Sunny</atmo_opacity><season>Month 10</season><ls>289.5</ls><sunrise>6 am</sunrise><sunset>5 pm</sunset></magnitudes></record><record><sol>227</sol><terrestrial_date>Mar 27, 2013 UTC</terrestrial_date><magnitudes><min_temp>-70.5</min_temp><max_temp>4.89</max_temp><pressure>8.929</pressure><pressure_string>Higher</pressure_string><abs_humidity>--</abs_humidity><wind_speed>2</wind_speed><wind_direction>E</wind_direction><atmo_opacity>Sunny</atmo_opacity><season>Month 10</season><ls>290.2</ls><sunrise>6 am</sunrise><sunset>5 pm</sunset></magnitudes></record><record><sol>228</sol><terrestrial_date>Mar 28, 2013 UTC</terrestrial_date><magnitudes><min_temp>-70.65</min_temp><max_temp>2.03</max_temp><pressure>8.9427</pressure><pressure_string>Higher</pressure_string><abs_humidity>--</abs_humidity><wind_speed>2</wind_speed><wind_direction>E</wind_direction><atmo_opacity>Sunny</atmo_opacity><season>Month 10</season><ls>290.8</ls><sunrise>6 am</sunrise><sunset>5 pm</sunset></magnitudes></record><record><sol>229</sol><terrestrial_date>Mar 29, 2013 UTC</terrestrial_date><magnitudes><min_temp>-69.26</min_temp><max_temp>1.39</max_temp><pressure>8.946</pressure><pressure_string>Higher</pressure_string><abs_humidity>--</abs_humidity><wind_speed>2</wind_speed><wind_direction>E</wind_direction><atmo_opacity>Sunny</atmo_opacity><season>Month 10</season><ls>291.7</ls><sunrise>6 am</sunrise><sunset>5 pm</sunset></magnitudes></record><record><sol>231</sol><terrestrial_date>Mar 31, 2013 UTC</terrestrial_date><magnitudes><min_temp>-70.95</min_temp><max_temp>1.73</max_temp><pressure>8.907</pressure><pressure_string>Higher</pressure_string><abs_humidity>--</abs_humidity><wind_speed>2</wind_speed><wind_direction>E</wind_direction><atmo_opacity>Sunny</atmo_opacity><season>Month 10</season><ls>292</ls><sunrise>6 am</sunrise><sunset>5 pm</sunset></magnitudes></record><record><sol>232</sol><terrestrial_date>Apr 1, 2012 UTC</terrestrial_date><magnitudes><min_temp>-68.99</min_temp><max_temp>1.95</max_temp><pressure>8.8832</pressure><pressure_string>Higher</pressure_string><abs_humidity>--</abs_humidity><wind_speed>2</wind_speed><wind_direction>E</wind_direction><atmo_opacity>Sunny</atmo_opacity><season>Month 10</season><ls>292.6</ls><sunrise>6 am</sunrise><sunset>5 pm</sunset></magnitudes></record><record><sol>231</sol><terrestrial_date>Apr 2, 2013 UTC</terrestrial_date><magnitudes><min_temp>-69.5</min_temp><max_temp>5.3</max_temp><pressure>8.902</pressure><pressure_string>Higher</pressure_string><abs_humidity>--</abs_humidity><wind_speed>2</wind_speed><wind_direction>E</wind_direction><atmo_opacity>Sunny</atmo_opacity><season>Month 10</season><ls>293.2</ls><sunrise>6 am</sunrise><sunset>5 pm</sunset></magnitudes></record><record><sol>231</sol><terrestrial_date>Apr 3, 2013 UTC</terrestrial_date><magnitudes><min_temp>-69.47</min_temp><max_temp>3.05</max_temp><pressure>8.8918</pressure><pressure_string>Higher</pressure_string><abs_humidity>--</abs_humidity><wind_speed>2</wind_speed><wind_direction>E</wind_direction><atmo_opacity>Sunny</atmo_opacity><season>Month 10</season><ls>293.8</ls><sunrise>6 am</sunrise><sunset>5 pm</sunset></magnitudes></record></climate_report>